mustafatik/__init__.py
mustafatik-0.0.7.dist-info/METADATA
mustafatik-0.0.7.dist-info/WHEEL
mustafatik-0.0.7.dist-info/top_level.txt
mustafatik-0.0.7.dist-info/RECORD
