Metadata-Version: 2.4
Name: mustafatik
Version: 0.0.7
Summary: A utility library for generating device and user-agent data.
Author-email: Mustafa <mustafa@example.com>
Classifier: Programming Language :: Python :: 3
Classifier: License :: OSI Approved :: MIT License
Classifier: Operating System :: OS Independent
Requires-Python: >=3.6
